MANIFEST.in
setup.py
mroy_trans.egg-info/PKG-INFO
mroy_trans.egg-info/SOURCES.txt
mroy_trans.egg-info/dependency_links.txt
mroy_trans.egg-info/entry_points.txt
mroy_trans.egg-info/not-zip-safe
mroy_trans.egg-info/requires.txt
mroy_trans.egg-info/top_level.txt
trans/README.md
trans/__init__.py
trans/back_query.py
trans/cmd.py
trans/msg