Metadata-Version: 1.0
Name: mroy-trans
Version: 0.9
Summary: a simple way to use mongo db, let db like dict
Home-page: https://github.com/Qingluan/mroy-trans.git
Author: Qing luan
Author-email: darkhackdevil@gmail.com
License: MIT
Platform: UNKNOWN
